{
    "hook_path": "models/hook/Hook47#6/base.urdf",
    "obj_path": "models/geo_data/hanging_exp/daily_5/base.urdf",
    "hook_pose": [
        0.5,
        -0.1,
        1.3,
        0.0,
        0.0,
        -0.7071067811865475,
        0.7071067811865476
    ],
    "contact_info": [
        {
            "contact_point_hook": [
                -0.005889712847716575,
                0.03495372505875727,
                -0.035642978511023715,
                1.0
            ],
            "contact_point_obj": [
                0.002110874946304582,
                -0.0048013274620937185,
                0.041051655423101296,
                1.0
            ],
            "obj_pose": [
                0.5305319983417291,
                -0.09621206309171862,
                1.2232622794633283,
                0.0033383533354223154,
                -0.005772813363463917,
                0.7458440895722876,
                0.6660871745297038
            ]
        }
    ]
}