{
    "hook_path": "models/hook_1120/Hook_180#21/base.urdf",
    "obj_path": "models/geo_data/hanging_exp/daily_5/base.urdf",
    "hook_pose": [
        0.5,
        -0.1,
        1.3,
        4.329780281177466e-17,
        0.7071067811865475,
        0.7071067811865476,
        4.329780281177467e-17
    ],
    "contact_info": [
        {
            "contact_point_hook": [
                0.00011396987067774367,
                -0.009799684699921984,
                0.031303094324923675,
                1.0
            ],
            "contact_point_obj": [
                -0.0049235317307314355,
                0.0004527046475029106,
                0.04720896821992526,
                1.0
            ],
            "obj_pose": [
                0.4986232189368828,
                -0.07357107940620983,
                1.243000945336886,
                -0.005054597244086424,
                0.005521010962894045,
                -0.7145560697412535,
                0.6995381281106702
            ]
        }
    ]
}